xlsm2spec/__init__.py
xlsm2spec/cli.py
xlsm2spec/application/__init__.py
xlsm2spec/application/analyzer.py
xlsm2spec/domain/__init__.py
xlsm2spec/domain/exceptions.py
xlsm2spec/domain/models.py
xlsm2spec/infrastructure/__init__.py
xlsm2spec/infrastructure/extractors/__init__.py
xlsm2spec/infrastructure/extractors/vba_extractor.py
xlsm2spec/infrastructure/parsers/__init__.py
xlsm2spec/infrastructure/parsers/vba_parser.py
xlsm2spec/infrastructure/readers/__init__.py
xlsm2spec/infrastructure/readers/excel_reader.py
xlsm2spec/presentation/__init__.py
xlsm2spec/presentation/formatters/__init__.py
xlsm2spec/presentation/formatters/ears_formatter.py
xlsm2spec/presentation/formatters/html_formatter.py
xlsm2spec/presentation/formatters/json_formatter.py
xlsm2spec/presentation/formatters/markdown_formatter.py
xlsm2spec-0.1.0.dist-info/METADATA
xlsm2spec-0.1.0.dist-info/WHEEL
xlsm2spec-0.1.0.dist-info/entry_points.txt
xlsm2spec-0.1.0.dist-info/RECORD
