Metadata-Version: 2.4
Name: xlsm2spec
Version: 0.1.0
Summary: Excel VBAを解析し仕様書を生成するCLIツール
Project-URL: Homepage, https://github.com/nahisaho/xlsm2spec
Project-URL: Repository, https://github.com/nahisaho/xlsm2spec
Project-URL: Issues, https://github.com/nahisaho/xlsm2spec/issues
Author: XLSM2Spec Team
License: MIT
Keywords: cli,documentation,excel,specification,vba
Classifier: Development Status :: 3 - Alpha
Classifier: Intended Audience :: Developers
Classifier: License :: OSI Approved :: MIT License
Classifier: Programming Language :: Python :: 3.11
Classifier: Programming Language :: Python :: 3.12
Classifier: Topic :: Documentation
Classifier: Topic :: Office/Business :: Office Suites
Requires-Python: >=3.11
Requires-Dist: oletools>=0.60.0
Requires-Dist: openpyxl>=3.1.0
Requires-Dist: rich>=13.0.0
Requires-Dist: typer>=0.9.0
Requires-Dist: xlrd>=2.0.0
Provides-Extra: dev
Requires-Dist: mypy>=1.6.0; extra == 'dev'
Requires-Dist: pytest-cov>=4.1.0; extra == 'dev'
Requires-Dist: pytest>=7.4.0; extra == 'dev'
Requires-Dist: ruff>=0.1.0; extra == 'dev'
